setup.py
inbox/__init__.py
inbox.egg-info/PKG-INFO
inbox.egg-info/SOURCES.txt
inbox.egg-info/dependency_links.txt
inbox.egg-info/requires.txt
inbox.egg-info/top_level.txt
nylas/__init__.py
nylas/_version.py
nylas/client/__init__.py
nylas/client/client.py
nylas/client/errors.py
nylas/client/restful_model_collection.py
nylas/client/restful_models.py
nylas/client/util.py