Metadata-Version: 1.0
Name: inbox
Version: 0.2.10
Summary: Python bindings for Nylas, the next-generation email platform.
Home-page: https://github.com/nylas/nylas-python
Author: Nylas Team
Author-email: support@nylas.com
License: MIT
Keywords: inbox app appserver email nylas
Platform: UNKNOWN
